claragenomics/__init__.py
claragenomics/bindings/__init__.py
claragenomics/bindings/cuda.cpp
claragenomics/bindings/cuda.cpython-37m-x86_64-linux-gnu.so
claragenomics/bindings/cudaaligner.cpp
claragenomics/bindings/cudaaligner.cpython-37m-x86_64-linux-gnu.so
claragenomics/bindings/cudapoa.cpp
claragenomics/bindings/cudapoa.cpython-37m-x86_64-linux-gnu.so
claragenomics/io/__init__.py
claragenomics/io/fastaio.py
claragenomics/io/pafio.py
claragenomics/io/utils.py
claragenomics/shared_libs/libcgaio.so
claragenomics/shared_libs/libcudaaligner.so
claragenomics/shared_libs/libcudapoa.so
claragenomics/shared_libs/liblogging.so
claragenomics/simulators/__init__.py
claragenomics/simulators/genomesim.py
claragenomics/simulators/readsim.py
claragenomics/utilities/__init__.py
claragenomics/utilities/utilities.py
claragenomics/wrappers/__init__.py
claragenomics/wrappers/wrappers.py
pyclaragenomics_cuda_10_1-0.4.3.data/data/cga_shared_objects/libcgaio.so
pyclaragenomics_cuda_10_1-0.4.3.data/data/cga_shared_objects/libcudaaligner.so
pyclaragenomics_cuda_10_1-0.4.3.data/data/cga_shared_objects/libcudapoa.so
pyclaragenomics_cuda_10_1-0.4.3.data/data/cga_shared_objects/liblogging.so
pyclaragenomics_cuda_10_1-0.4.3.data/scripts/assembly_evaluator
pyclaragenomics_cuda_10_1-0.4.3.data/scripts/genome_simulator
pyclaragenomics_cuda_10_1-0.4.3.dist-info/LICENSE
pyclaragenomics_cuda_10_1-0.4.3.dist-info/METADATA
pyclaragenomics_cuda_10_1-0.4.3.dist-info/WHEEL
pyclaragenomics_cuda_10_1-0.4.3.dist-info/top_level.txt
pyclaragenomics_cuda_10_1-0.4.3.dist-info/RECORD
