Metadata-Version: 2.1
Name: pyclaragenomics-cuda-10-1
Version: 0.4.3
Summary: NVIDIA genomics python libraries and utiliites
Home-page: https://github.com/clara-genomics/ClaraGenomicsAnalysis
Author: NVIDIA Corporation
License: Apache License 2.0
Platform: any
Classifier: Development Status :: 5 - Production/Stable
Classifier: Intended Audience :: Science/Research
Classifier: Topic :: Scientific/Engineering :: Bio-Informatics
Classifier: License :: OSI Approved :: Apache Software License
Classifier: Natural Language :: English
Classifier: Operating System :: POSIX :: Linux
Classifier: Programming Language :: Python :: 3.5
Classifier: Programming Language :: Python :: 3.6
Classifier: Programming Language :: Python :: 3.7
Classifier: Programming Language :: Python :: 3.8
Classifier: Programming Language :: Python :: 3.9
Requires-Python: >=3.5
Requires-Dist: Cython (==0.29.12)
Requires-Dist: flake8 (==3.7.8)
Requires-Dist: matplotlib (==3.0.3)
Requires-Dist: networkx (==2.4)
Requires-Dist: numpy (==1.16.3)
Requires-Dist: pytest (==4.4.1)
Requires-Dist: quast (==5.0.2)
Requires-Dist: sortedcollections (==1.1.2)
Requires-Dist: tqdm (==4.31.1)
